{"sections":{"slideshow":{"type":"slideshow","blocks":{"slide-1":{"type":"slide","settings":{"overlay_type":"gradient","overlay_background":"linear-gradient(180deg, rgba(0, 0, 0, 0), rgba(0, 0, 0, 0.8) 100%)","overlay_color":"#00000080","heading":"Power tools for every project","heading_size":"xl","subheading":"<p>Find trusted drills, sanders, planers, and multi purpose tools for everyday jobs and tougher projects.<\/p>","subheading_size":"lg","text_color":"#ffffff","box_align":"middle-center","content_width":60,"button_label":"Shop power tools","button_type_link":false,"button_color_scheme":"scheme-e7b82ab6-c85b-4c50-8a1a-c2d1f4fc2db3","link":"","secondary_button_label":"Explore the collections","secondary_button_type_link":true,"secondary_button_color_scheme":"","secondary_link":"","badge_overlay_line_1_text":"Up to","badge_overlay_line_1_font_size":"md","badge_overlay_line_2_text":"50%","badge_overlay_line_2_font_size":"xl","badge_overlay_line_3_text":"","badge_overlay_line_3_font_size":"md","badge_overlay_position":"left","badge_overlay_colors_text":"#ffffff","badge_overlay_colors_background":"#f17300","enable_video_mobile":false,"mobile_heading_size":"md","mobile_box_align":"bottom-left"}},"slide-2":{"type":"slide","settings":{"overlay_type":"gradient","overlay_background":"linear-gradient(180deg, rgba(0, 0, 0, 0), rgba(0, 0, 0, 0.8) 100%)","overlay_color":"#00000080","heading":"Tools for a better garden","heading_size":"xl","subheading":"<p>Find trusted drills, sanders, planers, and multi purpose tools for everyday jobs and tougher projects.<\/p>","subheading_size":"lg","text_color":"#ffffff","box_align":"middle-left","content_width":50,"button_label":"Shop garden tools","button_type_link":false,"button_color_scheme":"","link":"","secondary_button_label":"","secondary_button_type_link":false,"secondary_button_color_scheme":"","secondary_link":"","badge_overlay_line_1_text":"","badge_overlay_line_1_font_size":"md","badge_overlay_line_2_text":"","badge_overlay_line_2_font_size":"xl","badge_overlay_line_3_text":"","badge_overlay_line_3_font_size":"md","badge_overlay_position":"left","badge_overlay_colors_text":"#ffffff","badge_overlay_colors_background":"#004fc7","enable_video_mobile":false,"mobile_heading_size":"md","mobile_box_align":"bottom-left"}}},"block_order":["slide-1","slide-2"],"name":"t:sections.slideshow.blocks.slide.presets.name","settings":{"auto_rotate":false,"animation_type":"slide","navigation_position":"inside","change_slides_speed":5,"full_width":false,"slide_height":"large","accessibility_info":"","color_scheme":"","spacing_mode":"desktop","spacing_top":20,"spacing_bottom":20,"spacing_top_mobile":48,"spacing_bottom_mobile":48,"heading_tag":"h2","show_on_desktop":true,"show_on_mobile":true,"hide_if_empty":false}},"collection-list-1":{"type":"collection-list","blocks":{"collection-1":{"type":"collection","settings":{"collection":"","video_url":"","overlay_type":"gradient","overlay_background":"linear-gradient(180deg, rgba(0, 0, 0, 0) 1%, rgba(0, 0, 0, 0.8) 100%)","overlay_color":"#00000080","heading_size":"md","collection_description":"","button_text":"Shop now","button_type_link":false,"button_color_scheme":"button-primary","text_color":"#ffffff","box_align":"bottom-left","badge_overlay_line_1_text":"","badge_overlay_line_1_font_size":"sm","badge_overlay_line_2_text":"","badge_overlay_line_2_font_size":"md","badge_overlay_line_3_text":"","badge_overlay_line_3_font_size":"md","badge_overlay_position":"left","badge_overlay_colors_text":"#ffffff","badge_overlay_colors_background":"#b91212","mobile_heading_size":"md","mobile_box_align":"bottom-left"}},"collection-2":{"type":"collection","settings":{"collection":"","video_url":"","overlay_type":"gradient","overlay_background":"linear-gradient(180deg, rgba(0, 0, 0, 0) 2%, rgba(0, 0, 0, 0.8) 100%)","overlay_color":"#00000080","heading_size":"md","collection_description":"","button_text":"Shop now","button_type_link":false,"button_color_scheme":"button-primary","text_color":"#ffffff","box_align":"bottom-left","badge_overlay_line_1_text":"New","badge_overlay_line_1_font_size":"md","badge_overlay_line_2_text":"Arrivals","badge_overlay_line_2_font_size":"lg","badge_overlay_line_3_text":"","badge_overlay_line_3_font_size":"md","badge_overlay_position":"left","badge_overlay_colors_text":"#ffffff","badge_overlay_colors_background":"#0568ff","mobile_heading_size":"md","mobile_box_align":"bottom-left"}},"collection-3":{"type":"collection","settings":{"collection":"","video_url":"","overlay_type":"gradient","overlay_background":"linear-gradient(180deg, rgba(255, 255, 255, 0), rgba(0, 0, 0, 0.8) 100%)","overlay_color":"#00000080","heading_size":"md","collection_description":"","button_text":"Shop now","button_type_link":false,"button_color_scheme":"button-primary","text_color":"#ffffff","box_align":"bottom-left","badge_overlay_line_1_text":"","badge_overlay_line_1_font_size":"md","badge_overlay_line_2_text":"","badge_overlay_line_2_font_size":"xl","badge_overlay_line_3_text":"","badge_overlay_line_3_font_size":"md","badge_overlay_position":"left","badge_overlay_colors_text":"#ffffff","badge_overlay_colors_background":"#1e6568","mobile_heading_size":"md","mobile_box_align":"bottom-left"}}},"block_order":["collection-1","collection-2","collection-3"],"settings":{"heading":"","heading_size":"md","subheading":"","link_title":"All collections","link_url":"","headings_alignment":"left","card_ratio":"auto","show_title":true,"show_description":true,"show_button":true,"card_clickable_desktop":true,"links_new_window":false,"layout":"mosaic","columns":3,"stack_on_mobile":false,"color_scheme":"background-1","spacing_mode":"desktop","spacing_top":20,"spacing_bottom":30,"spacing_top_mobile":48,"spacing_bottom_mobile":48,"heading_tag":"h2","show_on_desktop":true,"show_on_mobile":true,"hide_if_empty":false}},"filters":{"type":"filters","blocks":{"filter-1":{"type":"filter","settings":{"title":"Brand","placeholder":"Choose a brand...","tooltip":"Start by picking your favorite tool brand."}},"filter-2":{"type":"filter","settings":{"title":"Category","placeholder":"Choose a category","tooltip":"Select the type of tool you're looking for."}},"filter-3":{"type":"filter","settings":{"title":"Power source","placeholder":"Choose a power source","tooltip":"Choose between cordless, corded, or fuel-powered tools."}}},"block_order":["filter-1","filter-2","filter-3"],"name":"t:sections.filters.presets.name","settings":{"heading":"","heading_size":"md","subheading":"","headings_alignment":"left","collections":[],"collections_2":[],"collections_label":"Select...","collections_tooltip":"","full_width":true,"height":"auto","height_custom":100,"color_scheme":"background-1","overlay_color":"","spacing_mode":"desktop","spacing_top":0,"spacing_bottom":60,"spacing_top_mobile":48,"spacing_bottom_mobile":48,"heading_tag":"h2","show_on_desktop":true,"show_on_mobile":true,"hide_if_empty":false}},"divider":{"type":"divider","name":"t:sections.divider.preset.name","settings":{"height":1,"width":1420,"color_background":"#dadada","spacing_mode":"desktop","spacing_top":0,"spacing_bottom":0,"spacing_top_mobile":48,"spacing_bottom_mobile":48}},"brands":{"type":"brands","blocks":{"collection-1":{"type":"collection","settings":{"collection":"","title":"","link":""}},"collection-2":{"type":"collection","settings":{"collection":"","title":"","link":""}},"collection-3":{"type":"collection","settings":{"collection":"","title":"","link":""}},"collection-4":{"type":"collection","settings":{"collection":"","title":"","link":""}},"collection-5":{"type":"collection","settings":{"collection":"","title":"","link":""}},"collection-6":{"type":"collection","settings":{"collection":"","title":"","link":""}},"collection-7":{"type":"collection","settings":{"collection":"","title":"","link":""}},"collection-8":{"type":"collection","settings":{"collection":"","title":"","link":""}}},"block_order":["collection-1","collection-2","collection-3","collection-4","collection-5","collection-6","collection-7","collection-8"],"disabled":true,"settings":{"heading":"Shop by brand","heading_size":"md","subheading":"","link_title":"","link_url":"","headings_alignment":"left","show_title":false,"links_new_window":false,"layout":"slider","move_one_slide":false,"auto_rotate":false,"change_slides_speed":3,"columns":6,"stack_on_mobile":false,"image_ratio":"adapt","color_scheme":"background-1","spacing_mode":"desktop","spacing_top":60,"spacing_bottom":60,"spacing_top_mobile":48,"spacing_bottom_mobile":48,"heading_tag":"h2","show_on_desktop":true,"show_on_mobile":true,"hide_if_empty":false}},"collection-list-2":{"type":"collection-list","blocks":{"collection-1":{"type":"collection","settings":{"collection":"","video_url":"","overlay_type":"gradient","overlay_background":"linear-gradient(194deg, rgba(0, 0, 0, 0), rgba(0, 0, 0, 0.4) 100%)","overlay_color":"#00000080","heading_size":"md","collection_description":"<p>Cut through tough jobs with ease using a reliable and efficient chainsaw, built for power and precision.<\/p>","button_text":"","button_type_link":false,"button_color_scheme":"button-primary","text_color":"#ffffff","box_align":"bottom-left","badge_overlay_line_1_text":"Up to","badge_overlay_line_1_font_size":"sm","badge_overlay_line_2_text":"50% Off!","badge_overlay_line_2_font_size":"xl","badge_overlay_line_3_text":"","badge_overlay_line_3_font_size":"md","badge_overlay_position":"left","badge_overlay_colors_text":"#f8f8f8","badge_overlay_colors_background":"#004fc7","mobile_heading_size":"md","mobile_box_align":"bottom-left"}},"collection-2":{"type":"collection","settings":{"collection":"","video_url":"","overlay_type":"gradient","overlay_background":"linear-gradient(180deg, rgba(0, 0, 0, 0), rgba(0, 0, 0, 0.4) 100%)","overlay_color":"#00000080","heading_size":"md","collection_description":"<p>Get the job done with much less effort with an affordable and powerful planer.<\/p>","button_text":"","button_type_link":false,"button_color_scheme":"button-primary","text_color":"#ffffff","box_align":"bottom-left","badge_overlay_line_1_text":"","badge_overlay_line_1_font_size":"md","badge_overlay_line_2_text":"","badge_overlay_line_2_font_size":"xl","badge_overlay_line_3_text":"","badge_overlay_line_3_font_size":"md","badge_overlay_position":"left","badge_overlay_colors_text":"#ffffff","badge_overlay_colors_background":"#004fc7","mobile_heading_size":"md","mobile_box_align":"bottom-left"}},"collection-3":{"type":"collection","settings":{"collection":"","video_url":"","overlay_type":"gradient","overlay_background":"linear-gradient(180deg, rgba(0, 0, 0, 0), rgba(0, 0, 0, 0.4) 100%)","overlay_color":"#00000080","heading_size":"md","collection_description":"<p>Keep your lawn perfectly trimmed with a cordless mower that delivers quiet, clean, and effortless performance.<\/p>","button_text":"","button_type_link":false,"button_color_scheme":"button-primary","text_color":"#ffffff","box_align":"bottom-left","badge_overlay_line_1_text":"","badge_overlay_line_1_font_size":"md","badge_overlay_line_2_text":"","badge_overlay_line_2_font_size":"xl","badge_overlay_line_3_text":"","badge_overlay_line_3_font_size":"md","badge_overlay_position":"left","badge_overlay_colors_text":"#ffffff","badge_overlay_colors_background":"#004fc7","mobile_heading_size":"md","mobile_box_align":"bottom-left"}},"collection-4":{"type":"collection","settings":{"collection":"","video_url":"","overlay_type":"gradient","overlay_background":"linear-gradient(180deg, rgba(0, 0, 0, 0), rgba(0, 0, 0, 0.4) 100%)","overlay_color":"#00000080","heading_size":"md","collection_description":"<p>Enjoy great prices on a wide range of hand tools from reputable brands.<\/p>","button_text":"","button_type_link":false,"button_color_scheme":"button-primary","text_color":"#ffffff","box_align":"bottom-left","badge_overlay_line_1_text":"","badge_overlay_line_1_font_size":"md","badge_overlay_line_2_text":"","badge_overlay_line_2_font_size":"xl","badge_overlay_line_3_text":"","badge_overlay_line_3_font_size":"md","badge_overlay_position":"left","badge_overlay_colors_text":"#ffffff","badge_overlay_colors_background":"#004fc7","mobile_heading_size":"md","mobile_box_align":"bottom-left"}},"collection-5":{"type":"collection","settings":{"collection":"","video_url":"","overlay_type":"gradient","overlay_background":"linear-gradient(180deg, rgba(0, 0, 0, 0), rgba(0, 0, 0, 0.4) 100%)","overlay_color":"#00000080","heading_size":"md","collection_description":"<p>Find the perfect orbital sander for all your needs like decorating and finishing work.<\/p>","button_text":"","button_type_link":false,"button_color_scheme":"button-primary","text_color":"#ffffff","box_align":"bottom-left","badge_overlay_line_1_text":"","badge_overlay_line_1_font_size":"md","badge_overlay_line_2_text":"","badge_overlay_line_2_font_size":"xl","badge_overlay_line_3_text":"","badge_overlay_line_3_font_size":"md","badge_overlay_position":"left","badge_overlay_colors_text":"#ffffff","badge_overlay_colors_background":"#004fc7","mobile_heading_size":"md","mobile_box_align":"bottom-left"}},"collection-6":{"type":"collection","settings":{"collection":"","video_url":"","overlay_type":"gradient","overlay_background":"linear-gradient(180deg, rgba(0, 0, 0, 0), rgba(0, 0, 0, 0.4) 100%)","overlay_color":"#00000080","heading_size":"md","collection_description":"<p>Clear leaves and debris in seconds with a lightweight cordless blower, designed for speed, control, and convenience.<\/p>","button_text":"","button_type_link":false,"button_color_scheme":"button-primary","text_color":"#ffffff","box_align":"bottom-left","badge_overlay_line_1_text":"","badge_overlay_line_1_font_size":"md","badge_overlay_line_2_text":"","badge_overlay_line_2_font_size":"lg","badge_overlay_line_3_text":"","badge_overlay_line_3_font_size":"md","badge_overlay_position":"left","badge_overlay_colors_text":"#232323","badge_overlay_colors_background":"#ff4f00","mobile_heading_size":"md","mobile_box_align":"bottom-left"}}},"block_order":["collection-1","collection-2","collection-3","collection-4","collection-5","collection-6"],"settings":{"heading":"Popular categories","heading_size":"md","subheading":"","link_title":"All categories","link_url":"shopify:\/\/collections","headings_alignment":"left","card_ratio":"auto","show_title":true,"show_description":false,"show_button":false,"card_clickable_desktop":true,"links_new_window":false,"layout":"mosaic","columns":3,"stack_on_mobile":false,"color_scheme":"background-1","spacing_mode":"desktop","spacing_top":60,"spacing_bottom":60,"spacing_top_mobile":48,"spacing_bottom_mobile":48,"heading_tag":"h2","show_on_desktop":true,"show_on_mobile":true,"hide_if_empty":false}},"collection-grid":{"type":"collection-grid","settings":{"heading":"Also popular","heading_size":"md","subheading":"","link_title":"All categories","link_url":"shopify:\/\/collections","headings_alignment":"left","collections":[],"show_image":true,"columns":5,"stack_on_mobile":true,"mobile_columns":"1","content_color_scheme":"","color_scheme":"background-1","spacing_mode":"desktop","spacing_top":60,"spacing_bottom":60,"spacing_top_mobile":48,"spacing_bottom_mobile":48,"heading_tag":"h2","show_on_desktop":true,"show_on_mobile":true,"hide_placeholders":false}},"countdown-banner":{"type":"countdown-banner","disabled":true,"settings":{"overlay_type":"gradient","overlay_background":"linear-gradient(128deg, rgba(0, 0, 0, 0.07), rgba(0, 0, 0, 0.69) 99%)","overlay_color":"#00000080","heading":"Special offers!","heading_size":"md","text":"<p>Our biggest deals of the year are here. Limited stock available.<\/p>","button_label":"Shop now","link":"","button_type_link":true,"end_date":"2026-07-09","end_time":"14:00:00","hide_on_expiration":false,"expiration_message":"","full_width":false,"mobile_heading_size":"md","button_type_link_mobile":false,"color_scheme":"accent-3","spacing_mode":"desktop","spacing_top":20,"spacing_bottom":60,"spacing_top_mobile":48,"spacing_bottom_mobile":48,"heading_tag":"h2","show_on_desktop":true,"show_on_mobile":true,"hide_if_empty":false}},"product-comparison":{"type":"product-comparison","blocks":{"price":{"type":"price","settings":{"heading":"Price"}},"stock_availability":{"type":"stock_availability","settings":{"heading":"Stock availability"}},"rating":{"type":"rating","settings":{"heading":"Rating"}},"vendor":{"type":"vendor","settings":{"heading":"Vendor"}},"sku":{"type":"sku","settings":{"heading":"SKU"}},"metafield-1":{"type":"metafield","settings":{"heading":"Watt (W)","metafield":"my_fields.watt"}},"metafield-2":{"type":"metafield","settings":{"heading":"Voltage (V)","metafield":"my_fields.voltage_v_"}},"metafield-3":{"type":"metafield","settings":{"heading":"Power source","metafield":"my_fields.power_source"}}},"block_order":["price","stock_availability","rating","vendor","sku","metafield-1","metafield-2","metafield-3"],"disabled":true,"name":"t:sections.product_comparison.presets.name","settings":{"heading":"Choose the right tool for the job","heading_size":"md","subheading":"","headings_alignment":"left","products":[],"show_current_product":false,"show_headings":true,"product_header_image_ratio":"square","product_header_add_to_cart_button":"view_product","product_header_show_quantity":false,"color_scheme":"background-1","spacing_mode":"desktop","spacing_top":60,"spacing_bottom":60,"spacing_top_mobile":48,"spacing_bottom_mobile":48,"heading_tag":"h2","show_on_desktop":true,"show_on_mobile":true,"hide_if_empty":false}},"scrolling-elements":{"type":"scrolling-elements","blocks":{"element-1":{"type":"element","settings":{"icon":"percent","text":"Deal of the day","link":""}},"element-2":{"type":"element","settings":{"icon":"percent","text":"Deal of the day","link":""}},"element-3":{"type":"element","settings":{"icon":"percent","text":"Deal of the day","link":""}},"element-4":{"type":"element","settings":{"icon":"percent","text":"Deal of the day","link":""}}},"block_order":["element-1","element-2","element-3","element-4"],"name":"t:sections.scrolling_elements.preset.name","settings":{"speed":30,"pause_on_hover":false,"direction":"left","full_width":true,"font_family":"body","text_size":16,"color_scheme":"accent-1","spacing_mode":"desktop","spacing_top":18,"spacing_bottom":18,"spacing_top_mobile":24,"spacing_bottom_mobile":24,"show_on_desktop":true,"show_on_mobile":true}},"featured-product":{"type":"featured-product","blocks":{"title":{"type":"title","settings":{"show_vendor":true,"show_stock":true,"show_sku":true,"show_barcode":false,"barcode_label":"Barcode","show_rating":false,"hide_empty_star_rating":false,"show_custom_badges":false,"show_bottom_divider":true,"block_heading_tag":"h2"}},"text":{"type":"text","settings":{"text":"","icon":"","text_2":"","icon_2":"","text_3":"","icon_3":"","text_4":"","icon_4":"","color_scheme":"none","show_bottom_divider":false}},"price":{"type":"price","settings":{"show_bottom_divider":false}},"range_indicator":{"type":"range_indicator","settings":{"label":"Performance Rating","range_from":1,"range_to":10,"value":"8","filled_color":"#007bff","track_color":"#e9ecef","show_bottom_divider":false}},"variants":{"type":"variants","settings":{"picker_type":"button","picker_equal_width":false,"picker_size":"normal","picker_shape":"inherit","hide_single_variant":false,"out_of_stock_variants":"show","show_bottom_divider":false}},"buy_buttons":{"type":"buy_buttons","settings":{"show_quantity":true,"show_add_to_cart":true,"show_buy_now":true,"show_gift_card_recipient":false,"button_color_scheme":"background-1","show_bottom_divider":false}}},"block_order":["title","text","price","range_indicator","variants","buy_buttons"],"settings":{"heading":"","heading_size":"md","subheading":"","headings_alignment":"left","product":"","preselect_variant":true,"hide_variants":false,"arrow_navigation":false,"thumbnails_position":"left","thumbnail_navigation":false,"image_zoom_type":"zoom_hover","image_ratio":"adapt","image_disclaimer":"","color_scheme":"background-2","spacing_mode":"desktop","spacing_top":60,"spacing_bottom":60,"spacing_top_mobile":48,"spacing_bottom_mobile":48,"heading_tag":"h2","show_on_desktop":true,"show_on_mobile":true,"hide_if_empty":false}},"video-background":{"type":"video-background","name":"t:sections.video_background.presets.name","settings":{"video_url":"https:\/\/www.youtube.com\/watch?v=_9VUPq3SxOc","overlay_type":"gradient","overlay_background":"linear-gradient(180deg, rgba(0, 0, 0, 0), rgba(0, 0, 0, 0.8) 100%)","overlay_color":"#00000080","video_description":"","heading":"Built for precision. Trusted by craftsmen.","heading_size":"xl","text":"<p>Weekend builder or a seasoned pro? These tools help bring your vision to life.<\/p>","text_size":"lg","button_label":"Shop Woodworking tools","button_type_link":false,"button_link":"","secondary_button_label":"","secondary_button_type_link":false,"secondary_button_link":"","full_width":false,"box_align":"middle-center","height":"large","mobile_heading_size":"lg","mobile_box_align":"middle-center","color_scheme":"","spacing_mode":"desktop","spacing_top":60,"spacing_bottom":60,"spacing_top_mobile":48,"spacing_bottom_mobile":48,"heading_tag":"h2","show_on_desktop":true,"show_on_mobile":true,"hide_if_empty":false}},"product-lists":{"type":"product-lists","blocks":{"product_list-1":{"type":"product_list","settings":{"overlay_type":"gradient","overlay_background":"linear-gradient(180deg, rgba(0, 0, 0, 0), rgba(0, 0, 0, 0.8) 100%)","overlay_color":"#00000080","heading":"Orbital sanders","description":"<p>Smooth surfaces fast<\/p>","link":"","products":[]}},"product_list-2":{"type":"product_list","settings":{"overlay_type":"gradient","overlay_background":"linear-gradient(180deg, rgba(0, 0, 0, 0), rgba(0, 0, 0, 0.8) 100%)","overlay_color":"#00000080","heading":"Planers","description":"<p>Perfect thickness, every time<\/p>","link":"","products":[]}},"product_list-3":{"type":"product_list","settings":{"overlay_type":"gradient","overlay_background":"linear-gradient(180deg, rgba(0, 0, 0, 0), rgba(0, 0, 0, 0.8) 100%)","overlay_color":"#00000080","heading":"Routers","description":"<p>Shape and edge with ease<\/p>","link":"","products":[]}}},"block_order":["product_list-1","product_list-2","product_list-3"],"disabled":true,"settings":{"heading":"Popular woodworking tools","heading_size":"md","subheading":"","headings_alignment":"left","link_title":"","link_url":"","columns":"3","stack_on_mobile":true,"card_ratio":"auto","color_scheme":"background-1","spacing_mode":"desktop","spacing_top":60,"spacing_bottom":60,"spacing_top_mobile":48,"spacing_bottom_mobile":48,"heading_tag":"h2","show_on_desktop":true,"show_on_mobile":true,"hide_if_empty":false}},"collection-tabs":{"type":"collection-tabs","blocks":{"collection-1":{"type":"collection","settings":{"collection":"","collection_tab_label":"","products":[]}},"collection-2":{"type":"collection","settings":{"collection":"","collection_tab_label":"","products":[]}},"collection-3":{"type":"collection","settings":{"collection":"","collection_tab_label":"","products":[]}}},"block_order":["collection-1","collection-2","collection-3"],"disabled":true,"settings":{"heading":"Popular brands","heading_size":"md","headings_alignment":"left","subheading":"","tab_display_mode":"text","tab_image_width":100,"auto_rotate":false,"change_slides_speed":5,"pause_on_hover":true,"products_to_show":8,"show_vendor":true,"show_sku":false,"show_stock":true,"show_rating":true,"layout":"slider","columns":"4","mobile_columns":"1","stack_on_mobile":false,"color_scheme":"background-2","spacing_mode":"desktop","spacing_top":60,"spacing_bottom":60,"spacing_top_mobile":48,"spacing_bottom_mobile":48,"heading_tag":"h2","show_on_desktop":true,"show_on_mobile":true,"hide_if_empty":false}},"sliding-panels":{"type":"sliding-panels","blocks":{"panel-1":{"type":"panel","settings":{"overlay_type":"gradient","overlay_background":"linear-gradient(180deg, rgba(0, 0, 0, 0), rgba(0, 0, 0, 0.3) 100%)","overlay_color":"#00000080","heading":"Hand Tools","heading_tag":"h2","heading_size":"lg","mobile_heading_size":"lg","text":"Professional grade sets for precision work.","text_color":"#ffffff","box_align":"middle-left","mobile_box_align":"middle-center","button_label":"Shop Hand Tools","button_link":"","button_color_scheme":""}},"panel-2":{"type":"panel","settings":{"overlay_type":"gradient","overlay_background":"linear-gradient(180deg, rgba(0, 0, 0, 0), rgba(0, 0, 0, 0.3) 100%)","overlay_color":"#00000080","heading":"Garden & Landscaping","heading_tag":"h2","heading_size":"lg","mobile_heading_size":"lg","text":"Tame the outdoors with powerful cordless mowers, trimmers, and landscaping essentials.","text_color":"#ffffff","box_align":"middle-left","mobile_box_align":"middle-center","button_label":"View Garden Range","button_link":"","button_color_scheme":""}},"panel-3":{"type":"panel","settings":{"overlay_type":"gradient","overlay_background":"linear-gradient(180deg, rgba(0, 0, 0, 0), rgba(0, 0, 0, 0.3) 100%)","overlay_color":"#00000080","heading":"Planers","heading_tag":"h2","heading_size":"lg","mobile_heading_size":"lg","text":"Achieve perfectly smooth surfaces and precise cuts with our high-performance electric planers.","text_color":"#ffffff","box_align":"middle-left","mobile_box_align":"middle-center","button_label":"Shop Planers","button_link":"","button_color_scheme":""}},"panel-4":{"type":"panel","settings":{"overlay_type":"gradient","overlay_background":"linear-gradient(180deg, rgba(0, 0, 0, 0), rgba(0, 0, 0, 0.3) 100%)","overlay_color":"#00000080","heading":"Cordless Leaf Blowers","heading_tag":"h2","heading_size":"lg","mobile_heading_size":"lg","text":"Lightweight designs engineered for maximum air velocity and battery life.","text_color":"#ffffff","box_align":"middle-left","mobile_box_align":"middle-center","button_label":"Shop Blowers","button_link":"","button_color_scheme":""}},"panel-5":{"type":"panel","settings":{"overlay_type":"gradient","overlay_background":"linear-gradient(180deg, rgba(0, 0, 0, 0), rgba(0, 0, 0, 0.3) 100%)","overlay_color":"#00000080","heading":"Chainsaws","heading_tag":"h2","heading_size":"lg","mobile_heading_size":"lg","text":"Cut through timber effortlessly with high-torque, heavy-duty chain systems.","text_color":"#ffffff","box_align":"middle-left","mobile_box_align":"middle-center","button_label":"Shop Chainsaws","button_link":"","button_color_scheme":""}}},"block_order":["panel-1","panel-2","panel-3","panel-4","panel-5"],"disabled":true,"name":"t:sections.sliding_panels.name","settings":{"initial_panel":1,"panel_height":"small","panel_gap":"tight","closed_title_size":"lg","color_scheme":"background-1","spacing_mode":"desktop","spacing_top":60,"spacing_bottom":60,"spacing_top_mobile":48,"spacing_bottom_mobile":48,"show_on_desktop":true,"show_on_mobile":true,"hide_if_empty":false}},"featured-collection":{"type":"featured-collection","disabled":true,"settings":{"heading":"Cordless tool kits","heading_size":"md","subheading":"","headings_alignment":"left","collection":"","products_to_show":7,"products":[],"show_vendor":true,"show_sku":false,"show_stock":true,"show_rating":true,"show_collection":true,"collection_position":"end","collection_overlay_type":"gradient","collection_overlay_background":"linear-gradient(180deg, rgba(0, 0, 0, 0), rgba(0, 0, 0, 0.8) 100%)","collection_overlay_color":"#00000080","collection_title":"","collection_description":"","hide_collection_description":false,"collection_text_color":"#ffffff","collection_button_text":"Shop now","collection_button_color_scheme":"","collection_box_align":"bottom-left","layout":"grid","columns":"4","stack_on_mobile":false,"mobile_columns":"2","color_scheme":"background-1","spacing_mode":"desktop","spacing_top":60,"spacing_bottom":60,"spacing_top_mobile":48,"spacing_bottom_mobile":48,"heading_tag":"h2","show_on_desktop":true,"show_on_mobile":true,"hide_placeholders":false}},"simple-collection-list":{"type":"simple-collection-list","blocks":{"collection-1":{"type":"collection","settings":{"collection":""}},"collection-2":{"type":"collection","settings":{"collection":""}},"collection-3":{"type":"collection","settings":{"collection":""}},"collection-4":{"type":"collection","settings":{"collection":""}},"collection-5":{"type":"collection","settings":{"collection":""}},"collection-6":{"type":"collection","settings":{"collection":""}},"collection-7":{"type":"collection","settings":{"collection":""}}},"block_order":["collection-1","collection-2","collection-3","collection-4","collection-5","collection-6","collection-7"],"disabled":true,"settings":{"heading":"You might also need","heading_size":"md","subheading":"","link_title":"All collections","link_url":"","headings_alignment":"left","image_ratio":"square","show_title":true,"block_heading_size":"md","enable_border":false,"layout":"grid","columns":7,"stack_on_mobile":false,"color_scheme":"background-1","spacing_mode":"desktop","spacing_top":60,"spacing_bottom":40,"spacing_top_mobile":48,"spacing_bottom_mobile":48,"heading_tag":"h2","show_on_desktop":true,"show_on_mobile":true,"hide_if_empty":false}},"media-with-text":{"type":"media-with-text","blocks":{"heading":{"type":"heading","settings":{"heading":"Serving the greater Athens area since 2000","heading_size":"md","heading_tag":"h2"}},"text":{"type":"text","settings":{"text":"<p>For more than two decades, we’ve been helping professionals and DIY enthusiasts find the right tools for every project. From trusted brands to expert guidance, our mission is to keep your work moving forward with quality you can rely on.<\/p>","text_size":"md"}},"button":{"type":"button","settings":{"button_label":"Learn more","button_link":"","link_new_window":false}}},"block_order":["heading","text","button"],"name":"t:sections.media_with_text.presets.name","settings":{"video_url":"","layout":"text_first","desktop_content_alignment":"left","enable_border_padding":true,"content_color_scheme":"background-1","color_scheme":"","spacing_mode":"desktop","spacing_top":40,"spacing_bottom":60,"spacing_top_mobile":48,"spacing_bottom_mobile":48,"show_on_desktop":true,"show_on_mobile":true,"hide_if_empty":false}},"blog-posts":{"type":"blog-posts","disabled":true,"settings":{"heading":"From the blog","heading_size":"md","subheading":"","link_title":"Visit our blog","link_url":"\/blogs\/news","headings_alignment":"left","blog":"news","posts_to_show":4,"show_date":true,"show_author":false,"show_excerpt":false,"columns":"4","stack_on_mobile":true,"color_scheme":"background-1","spacing_mode":"desktop","spacing_top":60,"spacing_bottom":60,"spacing_top_mobile":48,"spacing_bottom_mobile":48,"heading_tag":"h2","show_on_desktop":true,"show_on_mobile":true,"hide_if_empty":false}}},"order":["slideshow","collection-list-1","filters","divider","brands","collection-list-2","collection-grid","countdown-banner","product-comparison","scrolling-elements","featured-product","video-background","product-lists","collection-tabs","sliding-panels","featured-collection","simple-collection-list","media-with-text","blog-posts"]}